{
    "zones":
    [{
        "zone": "great_bilbao",
        "locations": ["bilbao"]
    },
    {
        "zone": "donostialdea",
        "locations": ["donostia"]
    },
    {
        "zone": "vitoria_gasteiz",
        "locations": ["gasteiz"]
    },
    {
        "zone": "cantabrian_valleys",
        "locations": ["amorebieta", "amurrio", "karrantza", "arrasate", "errezil"]
    },
    {
        "zone": "coast_zone",
        "locations": ["ondarroa", "bermeo"]
    },
    {
        "zone": "ebro_valley",
        "locations": ["lantaron"]
    },
    {
        "zone": "southern_mountain",
        "locations": ["lagran"]
    }]
}